MsFCoppel/Base.py
MsFCoppel/ColorJson.py
MsFCoppel/ErrorMs.py
MsFCoppel/Fork.py
MsFCoppel/ForkHttp.py
MsFCoppel/HttpErrors.py
MsFCoppel/HttpResponse.py
MsFCoppel/HttpTransit.py
MsFCoppel/LogssBottle.py
MsFCoppel/MsManager.py
MsFCoppel/NatsBase.py
MsFCoppel/Util.py
MsFCoppel/Worker.py
MsFCoppel/__init__.py
MsFCoppel/http_server.py
MsFCoppel/loggs.py
MsFCoppel/loggsWrapper.py
MsFCoppel/microservices.py
MsFCoppel/ms_base.py
MsFCoppel/options.py
MsFCoppel/types.py
MsFCoppel/version_framework.py
MsFCoppel-1.0.3.dist-info/LICENSE.txt
MsFCoppel-1.0.3.dist-info/METADATA
MsFCoppel-1.0.3.dist-info/WHEEL
MsFCoppel-1.0.3.dist-info/top_level.txt
MsFCoppel-1.0.3.dist-info/RECORD
